yahoo_fin/__init__.py
yahoo_fin/news.py
yahoo_fin/options.py
yahoo_fin/setup.py
yahoo_fin/stock_info.py
yahoo_fin-0.8.9.dist-info/METADATA
yahoo_fin-0.8.9.dist-info/WHEEL
yahoo_fin-0.8.9.dist-info/top_level.txt
yahoo_fin-0.8.9.dist-info/RECORD
