Metadata-Version: 1.0
Name: yahoo_fin
Version: 0.8.9
Summary: Download historical stock prices (daily / weekly / monthly),
Home-page: http://theautomatic.net/yahoo_fin-documentation/
Author: Andrew Treadway
Author-email: opensourcecoder11@gmail.com
License: MIT
Keywords: yahoo finance,stocks,options,fundamentals
Platform: UNKNOWN
